odoo/addons/gestion_editorial/CHANGELOG.md
odoo/addons/gestion_editorial/__init__.py
odoo/addons/gestion_editorial/__manifest__.py
odoo/addons/gestion_editorial/hooks.py
odoo/addons/gestion_editorial/data/ddaa_data.xml
odoo/addons/gestion_editorial/data/initial_data.xml
odoo/addons/gestion_editorial/data/promocion_data.xml
odoo/addons/gestion_editorial/data/purchase_deposit_data.xml
odoo/addons/gestion_editorial/i18n_extra/ca_ES.po
odoo/addons/gestion_editorial/i18n_extra/es.po
odoo/addons/gestion_editorial/migrations/17.0.1.0.1/post-migrate.py
odoo/addons/gestion_editorial/migrations/17.0.1.0.1/pre-migrate.py
odoo/addons/gestion_editorial/migrations/17.0.1.0.2/post-migrate.py
odoo/addons/gestion_editorial/migrations/17.0.1.0.2/pre-migrate.py
odoo/addons/gestion_editorial/migrations/17.0.1.1.2/post-migrate.py
odoo/addons/gestion_editorial/models/__init__.py
odoo/addons/gestion_editorial/models/account_editorial.py
odoo/addons/gestion_editorial/models/authorship_product.py
odoo/addons/gestion_editorial/models/ddaa_authorship_conditions.py
odoo/addons/gestion_editorial/models/liquidacion_editorial.py
odoo/addons/gestion_editorial/models/pos_order_editorial.py
odoo/addons/gestion_editorial/models/product_editorial.py
odoo/addons/gestion_editorial/models/product_pricelist_editorial.py
odoo/addons/gestion_editorial/models/purchase_order_editorial.py
odoo/addons/gestion_editorial/models/purchases_liquidation.py
odoo/addons/gestion_editorial/models/res_company_editorial.py
odoo/addons/gestion_editorial/models/res_config_settings_editorial.py
odoo/addons/gestion_editorial/models/res_partner_editorial.py
odoo/addons/gestion_editorial/models/sale_order_editorial.py
odoo/addons/gestion_editorial/models/sales_liquidation.py
odoo/addons/gestion_editorial/models/stock_location_editorial.py
odoo/addons/gestion_editorial/models/stock_move_editorial.py
odoo/addons/gestion_editorial/models/stock_picking_editorial.py
odoo/addons/gestion_editorial/models/stock_route_editorial.py
odoo_addon_gestion_editorial-17.0.1.6.0.dist-info/METADATA
odoo_addon_gestion_editorial-17.0.1.6.0.dist-info/WHEEL
odoo_addon_gestion_editorial-17.0.1.6.0.dist-info/top_level.txt
odoo_addon_gestion_editorial-17.0.1.6.0.dist-info/RECORD
