Metadata-Version: 2.1
Name: odoo-addon-gestion_editorial
Version: 17.0.1.6.0
Requires-Python: >=3.10
Requires-Dist: odoo-addon-account_invoice_pricelist>=17.0dev,<17.1dev
Requires-Dist: odoo-addon-product_dimension>=17.0dev,<17.1dev
Requires-Dist: odoo-addon-product_logistics_uom>=17.0dev,<17.1dev
Requires-Dist: odoo>=17.0a,<17.1dev
Summary: =?utf-8?q?M=C3=B3dulo_de_gesti=C3=B3n_para_entidades_del_mundo_del_libro?=
Home-page: https://framagit.org/devcontrol
License: OPL-1
Author: Colectivo DEVCONTROL
Classifier: Programming Language :: Python
Classifier: Framework :: Odoo
Classifier: Framework :: Odoo :: 17.0
